topsis_rhythm_102303707/__init__.py
topsis_rhythm_102303707/cli.py
topsis_rhythm_102303707/engine.py
topsis_rhythm_102303707-1.0.0.dist-info/METADATA
topsis_rhythm_102303707-1.0.0.dist-info/WHEEL
topsis_rhythm_102303707-1.0.0.dist-info/entry_points.txt
topsis_rhythm_102303707-1.0.0.dist-info/top_level.txt
topsis_rhythm_102303707-1.0.0.dist-info/RECORD
