Metadata-Version: 2.4
Name: topsis-rhythm-102303707
Version: 1.0.0
Summary: TOPSIS Multi-Criteria Decision Making Tool with CLI Support
Author: Rhythm Ghai
Requires-Dist: pandas
Requires-Dist: numpy
Dynamic: author
Dynamic: requires-dist
Dynamic: summary
